trunco/__init__.py
trunco/base.py
trunco/components/__init__.py
trunco/components/blockquote.py
trunco/components/button.py
trunco/components/checkbox.py
trunco/components/code.py
trunco/components/divider.py
trunco/components/form.py
trunco/components/heading.py
trunco/components/image.py
trunco/components/input.py
trunco/components/label.py
trunco/components/link.py
trunco/components/list.py
trunco/components/paragraph.py
trunco/components/preformattedText.py
trunco/components/radio.py
trunco/components/select.py
trunco/components/slider.py
trunco/components/table.py
trunco/components/textarea.py
trunco/enums.py
trunco-0.3.1.dist-info/LICENSE
trunco-0.3.1.dist-info/METADATA
trunco-0.3.1.dist-info/WHEEL
trunco-0.3.1.dist-info/RECORD
